{
  "project_info": {
    "project_number": "1090702154966",
    "firebase_url": "https://crypto-trader-d3041.firebaseio.com",
    "project_id": "crypto-trader-d3041",
    "storage_bucket": "crypto-trader-d3041.appspot.com"
  },
  "client": [
    {
      "client_info": {
        "mobilesdk_app_id": "1:1090702154966:android:db770aed5a52ecf28bfd77",
        "android_client_info": {
          "package_name": "com.platzi.android.firestore"
        }
      },
      "oauth_client": [
        {
          "client_id": "1090702154966-dk3poc9dqa9m518hfsgafdosl7724mkr.apps.googleusercontent.com",
          "client_type": 3
        }
      ],
      "api_key": [
        {
          "current_key": "AIzaSyANis6mH-h4pscsdiZpBbsyey8KWiq6Fgo"
        }
      ],
      "services": {
        "appinvite_service": {
          "other_platform_oauth_client": [
            {
              "client_id": "1090702154966-dk3poc9dqa9m518hfsgafdosl7724mkr.apps.googleusercontent.com",
              "client_type": 3
            }
          ]
        }
      }
    }
  ],
  "configuration_version": "1"
}